condax/__init__.py
condax/activation.py
condax/cli.py
condax/conda.py
condax/config.py
condax/core.py
condax/metadata.py
condax/paths.py
condax-0.2.4.dist-info/METADATA
condax-0.2.4.dist-info/WHEEL
condax-0.2.4.dist-info/entry_points.txt
condax-0.2.4.dist-info/licenses/LICENSE-MIT
condax-0.2.4.dist-info/RECORD
