Metadata-Version: 2.3
Name: condax
Version: 0.2.4
Summary: Install and run applications packaged with conda in isolated environments
Project-URL: Homepage, https://github.com/mariusvniekerk/condax
Project-URL: Documentation, https://mariusvniekerk.github.io/condax/
Author-email: Marius van Niekerk <marius.v.niekerk@gmail.com>
License-Expression: MIT
License-File: LICENSE-MIT
Classifier: Development Status :: 4 - Beta
Classifier: Intended Audience :: Developers
Classifier: License :: OSI Approved :: MIT License
Classifier: Programming Language :: Python :: 3 :: Only
Classifier: Topic :: System :: Installation/Setup
Requires-Python: >=3.8
Requires-Dist: click
Requires-Dist: ensureconda
Requires-Dist: pydantic-settings
Requires-Dist: pydantic>=2
Requires-Dist: pyyaml
Requires-Dist: requests
Requires-Dist: typer
Requires-Dist: userpath
